cross_cal_resourcesat/__init__.py
cross_cal_resourcesat/cross_cal_resourcesat.py
cross_cal_resourcesat/landsat.py
cross_cal_resourcesat-0.1.3.dist-info/LICENSE
cross_cal_resourcesat-0.1.3.dist-info/METADATA
cross_cal_resourcesat-0.1.3.dist-info/WHEEL
cross_cal_resourcesat-0.1.3.dist-info/dependency_links.txt
cross_cal_resourcesat-0.1.3.dist-info/top_level.txt
cross_cal_resourcesat-0.1.3.dist-info/RECORD
