Metadata-Version: 2.1
Name: cross-cal-resourcesat
Version: 0.1.3
Summary: A python package to cross calibrate ResourceSat 2 sensors like LISS III, AWiFS or LISS IV.
Home-page: https://github.com/akhi9661/cross_cal_resourcesat
Author: Akhilesh Kumar
Author-email: akhiraj9661@gmail.com
License: MIT license
Keywords: cross_cal_resourcesat
Classifier: Development Status :: 2 - Pre-Alpha
Classifier: Intended Audience :: Developers
Classifier: License :: OSI Approved :: MIT License
Classifier: Natural Language :: English
Classifier: Programming Language :: Python :: 3
Classifier: Programming Language :: Python :: 3.7
Classifier: Programming Language :: Python :: 3.8
Classifier: Programming Language :: Python :: 3.9
Classifier: Programming Language :: Python :: 3.10
Requires-Python: >=3.7
License-File: LICENSE
Requires-Dist: numpy
Requires-Dist: rasterio
Requires-Dist: glob2
Requires-Dist: regex
